{
  "source": "scheduled",
  "fetched_at": "2026-06-01T00:00:00+00:00",
  "provider": "DfT Street Manager / TfL planned works (bundled representative)",
  "streetworks": [
    {
      "id": "stw-whitechapel",
      "description": "Whitechapel Road \u2014 utility main replacement by Thames Water",
      "lat": 51.5175,
      "lng": -0.06,
      "start": "08:00",
      "end": "18:00",
      "date": "2026-06-05",
      "authority": "Tower Hamlets",
      "permit_reference": "SM-TFL-20260605-001",
      "traffic_management": "lane_closure",
      "severity": "severe"
    },
    {
      "id": "stw-strand",
      "description": "Strand \u2014 carriageway resurfacing",
      "lat": 51.511,
      "lng": -0.12,
      "start": "09:00",
      "end": "17:00",
      "date": "2026-06-06",
      "authority": "Westminster",
      "permit_reference": "SM-TFL-20260606-014",
      "traffic_management": "road_closure",
      "severity": "severe"
    },
    {
      "id": "stw-euston",
      "description": "Euston Road \u2014 gas mains renewal",
      "lat": 51.5246,
      "lng": -0.134,
      "start": "07:00",
      "end": "19:00",
      "date": "2026-06-07",
      "authority": "Camden",
      "permit_reference": "SM-TFL-20260607-021",
      "traffic_management": "multi_way_signals",
      "severity": "moderate"
    },
    {
      "id": "stw-waterloo",
      "description": "Waterloo Bridge approach \u2014 emergency telecoms duct works",
      "lat": 51.5085,
      "lng": -0.1175,
      "start": "08:30",
      "end": "16:30",
      "date": "2026-06-05",
      "authority": "Lambeth",
      "permit_reference": "SM-TFL-20260605-031",
      "traffic_management": "lane_closure",
      "severity": "severe"
    },
    {
      "id": "stw-holborn",
      "description": "Holborn Viaduct \u2014 burst water main repair",
      "lat": 51.517,
      "lng": -0.103,
      "start": "06:00",
      "end": "21:00",
      "date": "2026-06-05",
      "authority": "City of London",
      "permit_reference": "SM-TFL-20260605-044",
      "traffic_management": "contra_flow",
      "severity": "moderate"
    }
  ]
}
